kaggle_ex/__init__.py
kaggle_ex/climate_change_earth_surface_temperature.py
kagglebh-1.0.0.dist-info/METADATA
kagglebh-1.0.0.dist-info/WHEEL
kagglebh-1.0.0.dist-info/top_level.txt
kagglebh-1.0.0.dist-info/RECORD
