Metadata-Version: 2.1
Name: kagglebh
Version: 1.0.0
Summary: Analyze kaggle dataset: climate-change-earth-surface-temperature
Author-email: bart <henzel.b@gmail.com>
Project-URL: Homepage, https://github.com/HenzelBartlomiej/kaggle_datasets
Keywords: test,task
Requires-Python: >=3.8
Requires-Dist: kaggle
Requires-Dist: pyspark
Provides-Extra: dev
